{"name":"Beanz-Expersion-Language","className":"DataModel","filePaths":["default.project.json"],"children":[{"name":"ReplicatedStorage","className":"ReplicatedStorage","children":[{"name":"Constances","className":"Folder","children":[{"name":"IDK","className":"ModuleScript","filePaths":["src/Constances\\IDK.luau"]},{"name":"Types","className":"Folder","children":[{"name":"Compiler","className":"ModuleScript","filePaths":["src/Constances\\Types\\Compiler.luau"]}]}]},{"name":"Shared","className":"Folder","children":[{"name":"Compiler","className":"ModuleScript","filePaths":["src/shared\\Compiler\\init.luau"],"children":[{"name":"Compiler","className":"ModuleScript","filePaths":["src/shared\\Compiler\\Compiler\\init.luau"]},{"name":"Excutor","className":"ModuleScript","filePaths":["src/shared\\Compiler\\Excutor\\init.luau"],"children":[{"name":"Functions","className":"Folder","children":[{"name":"ABS","className":"ModuleScript","filePaths":["src/shared\\Compiler\\Excutor\\Functions\\ABS.luau"]},{"name":"ADD","className":"ModuleScript","filePaths":["src/shared\\Compiler\\Excutor\\Functions\\ADD.luau"]},{"name":"COS","className":"ModuleScript","filePaths":["src/shared\\Compiler\\Excutor\\Functions\\COS.luau"]},{"name":"DIV","className":"ModuleScript","filePaths":["src/shared\\Compiler\\Excutor\\Functions\\DIV.luau"]},{"name":"LOG","className":"ModuleScript","filePaths":["src/shared\\Compiler\\Excutor\\Functions\\LOG.luau"]},{"name":"MULTIPLY","className":"ModuleScript","filePaths":["src/shared\\Compiler\\Excutor\\Functions\\MULTIPLY.luau"]},{"name":"SET","className":"ModuleScript","filePaths":["src/shared\\Compiler\\Excutor\\Functions\\SET.luau"]},{"name":"SIN","className":"ModuleScript","filePaths":["src/shared\\Compiler\\Excutor\\Functions\\SIN.luau"]},{"name":"SQRT","className":"ModuleScript","filePaths":["src/shared\\Compiler\\Excutor\\Functions\\SQRT.luau"]},{"name":"SUB","className":"ModuleScript","filePaths":["src/shared\\Compiler\\Excutor\\Functions\\SUB.luau"]},{"name":"TAN","className":"ModuleScript","filePaths":["src/shared\\Compiler\\Excutor\\Functions\\TAN.luau"]},{"name":"WRITE","className":"ModuleScript","filePaths":["src/shared\\Compiler\\Excutor\\Functions\\WRITE.luau"]}]},{"name":"SpecialValues","className":"Folder","children":[{"name":"PI","className":"ModuleScript","filePaths":["src/shared\\Compiler\\Excutor\\SpecialValues\\PI.luau"]},{"name":"i","className":"ModuleScript","filePaths":["src/shared\\Compiler\\Excutor\\SpecialValues\\i.luau"]}]}]},{"name":"Util","className":"ModuleScript","filePaths":["src/shared\\Compiler\\Util\\init.luau"]},{"name":"ValidCharacterList","className":"ModuleScript","filePaths":["src/shared\\Compiler\\ValidCharacterList.luau"]}]}]}]},{"name":"ServerScriptService","className":"ServerScriptService","children":[{"name":"Server","className":"Script","filePaths":["src/server\\init.server.luau"]}]},{"name":"StarterPlayer","className":"StarterPlayer","children":[{"name":"StarterPlayerScripts","className":"StarterPlayerScripts","children":[{"name":"Client","className":"LocalScript","filePaths":["src/client\\init.client.luau"]}]}]}]}